mntfinder.py
mntfinder-1.1.0.dist-info/LICENSE
mntfinder-1.1.0.dist-info/METADATA
mntfinder-1.1.0.dist-info/WHEEL
mntfinder-1.1.0.dist-info/top_level.txt
mntfinder-1.1.0.dist-info/RECORD
