Metadata-Version: 2.1
Name: mntfinder
Version: 1.1.0
Summary: Parse /proc/mounts and find/list mountpoints (Not a wrapper of findmnt)
Author: nukemiko
License: MIT License
Project-URL: Repository, https://github.com/nukemiko/python-mntfinder
Project-URL: Issues, https://github.com/nukemiko/python-mntfinder/issues
Project-URL: Changelog, https://github.com/nukemiko/python-mntfinder/blob/master/CHANGELOG.md
Keywords: mountpoint,mnt,findmnt
Classifier: Programming Language :: Python :: 3
Classifier: License :: OSI Approved :: MIT License
Classifier: Operating System :: POSIX
Requires-Python: >=3.10
License-File: LICENSE
Requires-Dist: attrs
